sslcommerz_python/__init__.py
sslcommerz_python/_constants.py
sslcommerz_python/payment.py
sslcommerz_python_package-0.0.8.dist-info/LICENSE
sslcommerz_python_package-0.0.8.dist-info/METADATA
sslcommerz_python_package-0.0.8.dist-info/WHEEL
sslcommerz_python_package-0.0.8.dist-info/top_level.txt
sslcommerz_python_package-0.0.8.dist-info/RECORD
