Metadata-Version: 2.1
Name: sslcommerz-python-package
Version: 0.0.8
Summary: Implements SSLCOMMERZ payment gateway in python based web apps.
Home-page: https://github.com/sazzadhossain881/sslcommerz-python-1.0.0
Author: Sazzad Hossain
Author-email: sajjadhossain342@gmail.com
Classifier: Programming Language :: Python :: 3
Classifier: License :: OSI Approved :: MIT License
Classifier: Operating System :: OS Independent
Requires-Python: >=3.6
License-File: LICENSE
Requires-Dist: astroid ==2.3.3
Requires-Dist: certifi ==2019.11.28
Requires-Dist: chardet ==3.0.4
Requires-Dist: idna ==2.8
Requires-Dist: isort ==4.3.21
Requires-Dist: lazy-object-proxy ==1.4.3
Requires-Dist: mccabe ==0.6.1
Requires-Dist: requests ==2.22.0
Requires-Dist: six ==1.13.0
Requires-Dist: typed-ast ==1.4.0
Requires-Dist: urllib3 ==1.25.7
Requires-Dist: wrapt ==1.11.2
